chatgpt_meraki_analyzer/__init__.py
chatgpt_meraki_analyzer/chatgpt_meraki_analyzer.py
chatgpt_meraki_analyzer/script.py
chatgpt_meraki_analyzer-0.1.1.dist-info/LICENSE
chatgpt_meraki_analyzer-0.1.1.dist-info/METADATA
chatgpt_meraki_analyzer-0.1.1.dist-info/WHEEL
chatgpt_meraki_analyzer-0.1.1.dist-info/entry_points.txt
chatgpt_meraki_analyzer-0.1.1.dist-info/RECORD
