Metadata-Version: 2.1
Name: chatgpt-meraki-analyzer
Version: 0.1.1
Summary: A chatGPT powered Meraki analyzer
Author: John Capobianco
Author-email: ptcapo@gmail.com
Requires-Python: >=3.8,<4.0
Classifier: Programming Language :: Python :: 3
Classifier: Programming Language :: Python :: 3.8
Classifier: Programming Language :: Python :: 3.9
Classifier: Programming Language :: Python :: 3.10
Classifier: Programming Language :: Python :: 3.11
Requires-Dist: meraki (>=1.27.0,<2.0.0)
Requires-Dist: openai (>=0.27.2,<0.28.0)
Requires-Dist: python-dotenv (>=1.0.0,<2.0.0)
Requires-Dist: requests (>=2.28.2,<3.0.0)
Requires-Dist: rich-click (>=1.6.1,<2.0.0)
